{
    "Border": {
        "SomeDetails": "Points and lines should be in counterclockwise order. SourcesIDs is array of pairs - where first number - is related branch id(source branche), and second is index of related point in coords array(after initialization it will be source point of related branch). Lines consist of three numbers: first and second - point index in coords array, third - configures boundary condition(See --boundary-condition option in program: ./riversim -h).",
        "SourceIds": [
            [
                1,
                4
            ],
            [
                2,
                5
            ]
        ],
        "coords": [
            [
                2.0,
                0.0
            ],
            [
                2.0,
                50.0
            ],
            [
                0.0,
                50.0
            ],
            [
                0.0,
                0.0
            ],
            [
                0.7,
                0.0
            ],
            [
                1.3,
                0.0
            ]
        ],
        "lines": [
            [
                0,
                1,
                1
            ],
            [
                1,
                2,
                2
            ],
            [
                2,
                3,
                3
            ],
            [
                3,
                4,
                4
            ],
            [
                4,
                5,
                4
            ],
            [
                5,
                0,
                4
            ]
        ]
    },
    "Description": "RiverSim simulation data and state of program. All coordinates are in normal cartesian coordinate system and by default are x > 0 and y > 0. Default values of simulation assumes that coordinates values will be of order 0 - 200. Greater values demands a lot of time to run, small are not tested(Problem of scalling isn't resolved yet TODO).",
    "GeometryDifference": {
        "AlongBranches": [
            [
                1,
                [
                    [
                        4.0750128989483145e-05,
                        4.11286221035054e-05,
                        4.424309338722253e-05,
                        4.617391155613753e-05,
                        4.704677245026978e-05,
                        4.8148245965384643e-05,
                        5.296756035237363e-05,
                        5.441069792664774e-05,
                        5.2072032641636714e-05,
                        5.458531489499239e-05,
                        5.659719177535363e-05,
                        5.686213409152373e-05,
                        5.84873898847366e-05,
                        6.090784155490181e-05,
                        6.299307937926764e-05,
                        6.581010751140913e-05,
                        6.692999996206624e-05,
                        6.756102186361694e-05,
                        6.639109821394268e-05,
                        7.01742733817706e-05,
                        6.947690337734421e-05,
                        7.057010126102938e-05,
                        7.276340157283215e-05,
                        6.78878342830187e-05,
                        7.128746664490349e-05
                    ],
                    [
                        0.0003991122690966653,
                        0.00041079634864568974,
                        0.000420174754615253,
                        0.000430283837246793,
                        0.00043996258194258636,
                        0.0004489850232911886,
                        0.00045773267304112416,
                        0.00046582166842562615,
                        0.00047461781832751565,
                        0.0004804368325896297,
                        0.00048769713807464974,
                        0.0004938942188038102,
                        0.0004987054785553286,
                        0.0005044380635081618,
                        0.0005081476154528222,
                        0.000511752141544616,
                        0.0005146632444253627,
                        0.0005164183995157381,
                        0.0005182049596426063,
                        0.0005196677748656445,
                        0.0005191227956299801,
                        0.0005188895980589107,
                        0.0005177269496462533,
                        0.0005165343662442521,
                        0.0005134596559631228
                    ],
                    [
                        3.4628000615705488,
                        3.6263448011209527,
                        3.797037915548441,
                        3.9740891354129064,
                        4.157900663644024,
                        4.348396254939359,
                        4.545396882925618,
                        4.748906451847465,
                        4.958690593053055,
                        5.175093677780026,
                        5.396887604891061,
                        5.624761859591144,
                        5.858223210166712,
                        6.096669738293051,
                        6.340571315805622,
                        6.588938906802934,
                        6.841719543336169,
                        7.098508367195795,
                        7.3586774729538895,
                        7.622118014782254,
                        7.888782409242849,
                        8.157408438513864,
                        8.428131943768737,
                        8.700429908889765,
                        8.973806303625592
                    ],
                    [
                        0.0231394439227459,
                        0.0039028635742261444,
                        0.009397272314280279,
                        0.005359372769837697,
                        0.005724248922419397,
                        0.009574236673341296,
                        0.011868682166723146,
                        0.0027588596998675144,
                        0.005340169277834978,
                        0.018830075855845285,
                        0.017049621449565965,
                        0.016423461786699154,
                        0.022008686737282675,
                        0.022608860809507896,
                        0.020104976233491532,
                        0.02154374331162608,
                        0.01646263437018891,
                        0.021802973092300386,
                        0.023375213863482004,
                        0.030436565333366552,
                        0.026656003980828617,
                        0.034398174413668874,
                        0.034484467504748484,
                        0.03612220037700621,
                        0.05314320449468292
                    ],
                    [
                        2.4011076352420875,
                        2.554034241428149,
                        2.634336761931415,
                        2.7928060591109447,
                        2.911399651454954,
                        3.102744783548225,
                        3.238557107041301,
                        3.4132288248165583,
                        3.497052160245026,
                        3.6860614553972297,
                        3.845268170499443,
                        4.0604524722370385,
                        4.194849707559604,
                        4.339083183366626,
                        4.544236638311489,
                        4.673135806664507,
                        4.844601932241788,
                        5.0521073521446125,
                        5.23974372133917,
                        5.405566946478612,
                        5.544804260316823,
                        5.707275036295384,
                        5.8479625118442184,
                        6.053489047496438,
                        6.13426590441122
                    ]
                ]
            ],
            [
                2,
                [
                    [
                        9.303385781519728e-07,
                        6.745141922090346e-07,
                        2.303663616439751e-07,
                        -5.960464477539064e-08,
                        -4.860611686199978e-07,
                        -9.844921028113125e-07,
                        -1.5537274357960684e-06,
                        -2.133365479037779e-06,
                        -2.7626688554897337e-06,
                        -3.764305846754821e-06,
                        -4.304217886207504e-06,
                        -5.084135570968136e-06,
                        -5.996787142741198e-06,
                        -7.062615955846405e-06,
                        -8.21450078638178e-06,
                        -9.226743179870169e-06,
                        -1.0454521312965201e-05,
                        -8.939616316873728e-06,
                        3.832554325826801e-06,
                        -1.4060096435116936e-06,
                        -1.611917916487392e-05,
                        -1.757099031016476e-05,
                        -3.3394532868085925e-05,
                        -3.324180884215327e-05,
                        -9.705198468899426e-06
                    ],
                    [
                        1.0388707821063319e-05,
                        8.072277058377884e-06,
                        3.7756578545620537e-06,
                        1.1856547856305795e-06,
                        2.408246284410624e-06,
                        6.032733789950515e-06,
                        1.034458552159911e-05,
                        1.4532496471575323e-05,
                        1.8647261072711683e-05,
                        2.37365090583513e-05,
                        2.8247854784306954e-05,
                        3.255462252494471e-05,
                        3.746316798733423e-05,
                        4.3564977519148144e-05,
                        4.824023192981915e-05,
                        5.3825392926658394e-05,
                        5.8925255035406546e-05,
                        6.41086883558776e-05,
                        8.4483304112349e-05,
                        8.326970718307656e-05,
                        8.150897410183438e-05,
                        8.661738151366527e-05,
                        0.00011440567994123895,
                        0.00011468862611850529,
                        0.00010312702262746655
                    ],
                    [
                        26.110232670442205,
                        26.11798219620708,
                        26.12399832169481,
                        26.126781477561195,
                        26.127507291547722,
                        26.125938617443794,
                        26.121599080187625,
                        26.114019963049735,
                        26.10331904968779,
                        26.089578369438144,
                        26.07219789990481,
                        26.051383257965263,
                        26.027425388945982,
                        25.999892961394263,
                        25.967884949161423,
                        25.932602849352733,
                        25.893227517468283,
                        25.85026126283846,
                        25.802924970243154,
                        25.753271885441276,
                        25.697998259442908,
                        25.639267820992387,
                        25.57704884748298,
                        25.510923535312187,
                        25.442225748074154
                    ],
                    [
                        0.06652257048229403,
                        0.0338477098283795,
                        0.05755482187027266,
                        0.013980734159532202,
                        0.08203703032628935,
                        0.02691173870755749,
                        0.035481047921523345,
                        0.008964621911060369,
                        -0.008207306266304169,
                        0.028310484286307516,
                        -0.07035669747633677,
                        -0.020797138606612732,
                        -0.01344106895384577,
                        -0.03558804167270392,
                        -0.030121413348162932,
                        -0.07013907559579668,
                        -0.03991884280984224,
                        -0.09453688322099216,
                        -0.12256968430910836,
                        -0.1551083711293789,
                        -0.12115918968283378,
                        -0.061836763221780756,
                        -0.034819486811943176,
                        -0.07319746987801717,
                        -0.07428422204598685
                    ],
                    [
                        6.383877907367007,
                        6.462561923094663,
                        6.468009525172906,
                        6.6408343259946845,
                        6.518499176682885,
                        6.390774333764101,
                        6.683081169929451,
                        6.78685615407707,
                        6.791204699822274,
                        6.443367623368517,
                        6.842525702802101,
                        7.082265921938462,
                        6.866550246095042,
                        7.2044113137294135,
                        6.991307049225788,
                        7.240044820080094,
                        7.149828498121477,
                        7.120763478183574,
                        6.921918644708017,
                        7.11188380602367,
                        7.227160672605527,
                        7.394598111613924,
                        7.460428438250302,
                        7.502218280714332,
                        7.782215121516063
                    ]
                ]
            ]
        ],
        "BiffuractionPoints": [],
        "Description": "This structure holds info about backward river simulation. AlongBranches consist of five arrays for each branch: {branch_id: {1..}, {2..}, {3..}, {4..}, {5..}}, Where first consist of angles values allong branch(from tip to source), second - distance between tips, third - a(1) elements, forth - a(2) elements, fifth - a(3) elements. In case of --simulation-type=2, first item - integral value over whole region, second - disk integral over tip with r = 0.1, and rest are series params. BiffuractionPoints - is similar to previous object. It has same parameters but in biffurcation point. {source_branch_id: {lenght of non zero branch, which doesnt reached biffurcation point as its adjacent branch},{a(1)},{a(2)},{a(3)}}."
    },
    "Model": {
        "Description": "All model parameters. Almost all options are described in program options: ./riversim -h. riverBoundaryId - value of boundary id of river(solution equals zero on river boundary) ",
        "Integration": {
            "exponant": 2.0,
            "radius": 0.03,
            "weightRadius": 0.01
        },
        "Mesh": {
            "eps": 1e-06,
            "exponant": 7.0,
            "maxArea": 100000.0,
            "maxEdge": 1.0,
            "minAngle": 30.0,
            "minArea": 7e-08,
            "minEdge": 8e-08,
            "numberOfQuadrangles": 7278,
            "numberOfRefinedQuadrangles": 138366,
            "ratio": 2.3,
            "refinmentRadius": 0.04,
            "sigma": 1.9,
            "staticRefinmentSteps": 3
        },
        "Solver": {
            "adaptiveRefinmentSteps": 0,
            "iterationSteps": 6000,
            "quadratureDegree": 3,
            "refinmentFraction": 0.1,
            "tol": 1e-12
        },
        "biffurcationAngle": 0.6283185307179586,
        "biffurcationMinDistance": 0.05,
        "biffurcationThreshold": -0.1,
        "biffurcationThreshold2": 0.001,
        "biffurcationType": 3,
        "boundaryCondition": 1,
        "boundaryIds": [
            1,
            2,
            3,
            4
        ],
        "ds": 0.05,
        "dx": 0.2,
        "eta": 0.7,
        "fieldValue": 1.0,
        "growthMinDistance": 0.01,
        "growthThreshold": 0.0,
        "growthType": 0,
        "height": 50.0,
        "numberOfBackwardSteps": 1,
        "riverBoundaryId": 4,
        "width": 2.0
    },
    "RuntimeInfo": {
        "Description": "Units are in seconds.",
        "EachCycleTime": [
            1757.13,
            1647.35,
            1688.72,
            1686.37,
            1760.44,
            1744.57,
            1665.56,
            1764.99,
            1779.83,
            1680.78,
            1611.1,
            1648.8,
            1807.26,
            1828.83,
            1775.47,
            1752.42,
            1771.34,
            1843.55,
            1762.86,
            1796.71,
            1831.7,
            1684.91,
            1639.49,
            1712.63,
            1696.73
        ],
        "EndDate": "Sat Jan 11 20:58:40 2020\n",
        "InputFile": "/home/stzukowski/riversim/dev/riversim/archive/stzukowski/initialLength1/cut_rivers/lap7.json",
        "MaximalRiverHeight": 5.5,
        "NumberOfSteps": 25,
        "StartDate": "Sat Jan 11 08:42:33 2020\n",
        "TotalTime": 43339.53999999999
    },
    "Trees": {
        "Branches": [
            {
                "Desciption": "Order of elements should be from source point to tip. Source point should be the same as first point of array. Source angle - represents branch growth dirrection when it consist only from one(source) point. For example perpendiculary to border line. Id should be unique(and >= 1) to each branch and is referenced in Trees->Relations structure and Border->SourcesId",
                "coords": [
                    [
                        0.7,
                        0.0
                    ],
                    [
                        0.7,
                        0.01
                    ],
                    [
                        0.6999972116790069,
                        0.041195005238729335
                    ],
                    [
                        0.6999331363020491,
                        0.0790427513538847
                    ],
                    [
                        0.6996546950635157,
                        0.11953807912100556
                    ],
                    [
                        0.6990296472471916,
                        0.16131089210774197
                    ],
                    [
                        0.697900919996551,
                        0.2037441613780291
                    ],
                    [
                        0.6960846806153176,
                        0.24650285019531204
                    ],
                    [
                        0.6934961155138117,
                        0.28938421626998445
                    ],
                    [
                        0.6901048431168824,
                        0.33225552200155045
                    ],
                    [
                        0.685892670107077,
                        0.37502429736325776
                    ],
                    [
                        0.6808899427574571,
                        0.41762747310833936
                    ],
                    [
                        0.6751294001916744,
                        0.4600179343231945
                    ],
                    [
                        0.6686978030500219,
                        0.5021660802349748
                    ],
                    [
                        0.6616940549815213,
                        0.5440519684335088
                    ],
                    [
                        0.6541816639849443,
                        0.5856582273207748
                    ],
                    [
                        0.6462616418290248,
                        0.626976620455497
                    ],
                    [
                        0.6380037346645905,
                        0.6679977955083796
                    ],
                    [
                        0.6294735172095087,
                        0.7087140704735327
                    ],
                    [
                        0.6207781083010606,
                        0.7491288563904676
                    ],
                    [
                        0.6119471728849152,
                        0.7892324354077355
                    ],
                    [
                        0.6030576197107644,
                        0.8290228463684346
                    ],
                    [
                        0.5941545142517102,
                        0.8684940702162506
                    ],
                    [
                        0.5852954491852432,
                        0.9076446598015904
                    ],
                    [
                        0.5765093685579191,
                        0.9464674874068304
                    ],
                    [
                        0.5678253945713579,
                        0.9849564760524082
                    ],
                    [
                        0.5592710734050189,
                        1.0231041097330609
                    ],
                    [
                        0.5508632076660113,
                        1.0609012289924313
                    ],
                    [
                        0.5426199190493124,
                        1.0983399948869261
                    ],
                    [
                        0.5345385351043336,
                        1.1354099169222385
                    ],
                    [
                        0.5266609887428064,
                        1.1721069100177657
                    ],
                    [
                        0.518990825057159,
                        1.2084232993260833
                    ],
                    [
                        0.5115299287731744,
                        1.2443477063804473
                    ],
                    [
                        0.5042895442013685,
                        1.2798736106083606
                    ],
                    [
                        0.49723786093792344,
                        1.3149835663471339
                    ],
                    [
                        0.49040407243054834,
                        1.3496759868567683
                    ],
                    [
                        0.4837778657968752,
                        1.3839391511524561
                    ],
                    [
                        0.4773558745535634,
                        1.4177644446088837
                    ],
                    [
                        0.47113172423244365,
                        1.4511427463874746
                    ],
                    [
                        0.4650885632837247,
                        1.4840632215362046
                    ],
                    [
                        0.4592188254339348,
                        1.5165165401645213
                    ],
                    [
                        0.45352674064430165,
                        1.5484961556200958
                    ],
                    [
                        0.44801231249332346,
                        1.5799964921037377
                    ],
                    [
                        0.44266340708105667,
                        1.6110076661692054
                    ],
                    [
                        0.43747557928254355,
                        1.6415236478933837
                    ],
                    [
                        0.43243469212995517,
                        1.6715375309197658
                    ],
                    [
                        0.42754928730593733,
                        1.7010439735950684
                    ],
                    [
                        0.4228199515979253,
                        1.7300377399415956
                    ],
                    [
                        0.41823563286948334,
                        1.7585149690942572
                    ],
                    [
                        0.4137938174147407,
                        1.7864692368718171
                    ],
                    [
                        0.40948210713323074,
                        1.8138962459367143
                    ],
                    [
                        0.40530287097602324,
                        1.8407925124678852
                    ],
                    [
                        0.4012435928026913,
                        1.8671540172488486
                    ],
                    [
                        0.3973044233162178,
                        1.8929787329045524
                    ],
                    [
                        0.39347909113421514,
                        1.9182654643746995
                    ],
                    [
                        0.3897704045109049,
                        1.9430123480644146
                    ],
                    [
                        0.3882356810062189,
                        1.9533102252700858
                    ]
                ],
                "id": 1,
                "sourceAngle": 1.5707963267948966,
                "sourcePoint": [
                    0.7,
                    0.0
                ]
            },
            {
                "Desciption": "Order of elements should be from source point to tip. Source point should be the same as first point of array. Source angle - represents branch growth dirrection when it consist only from one(source) point. For example perpendiculary to border line. Id should be unique(and >= 1) to each branch and is referenced in Trees->Relations structure and Border->SourcesId",
                "coords": [
                    [
                        1.3,
                        0.0
                    ],
                    [
                        1.3,
                        0.04
                    ],
                    [
                        1.3000160371023448,
                        0.08999999742811343
                    ],
                    [
                        1.3000433834928085,
                        0.13999998994986215
                    ],
                    [
                        1.3001535892259797,
                        0.1899998684966784
                    ],
                    [
                        1.3004554552678393,
                        0.23999895725730255
                    ],
                    [
                        1.3010428784268167,
                        0.28999550647854677
                    ],
                    [
                        1.302046648446912,
                        0.3399854299206442
                    ],
                    [
                        1.3034984650375765,
                        0.3899643477619407
                    ],
                    [
                        1.3053982934699726,
                        0.4399282412444092
                    ],
                    [
                        1.3077181038991879,
                        0.48987439704815955
                    ],
                    [
                        1.3104297389393276,
                        0.5398008132565064
                    ],
                    [
                        1.3135097878677144,
                        0.5897058560738284
                    ],
                    [
                        1.316850383869526,
                        0.6395941354423602
                    ],
                    [
                        1.3204024034023185,
                        0.6894678074270724
                    ],
                    [
                        1.324081430107149,
                        0.739332271351847
                    ],
                    [
                        1.3278273100827094,
                        0.7891917577431917
                    ],
                    [
                        1.331606218233256,
                        0.8390487517679996
                    ],
                    [
                        1.3353378392214772,
                        0.8889093073685971
                    ],
                    [
                        1.3389957682312232,
                        0.9387753234051691
                    ],
                    [
                        1.3425162065557161,
                        0.9886512345648005
                    ],
                    [
                        1.3458961135434855,
                        1.0385368660507708
                    ],
                    [
                        1.3491174268392447,
                        1.0884329895540106
                    ],
                    [
                        1.3521209591980505,
                        1.1383426959583725
                    ],
                    [
                        1.3548903546952276,
                        1.1882659415317545
                    ],
                    [
                        1.3573671231235451,
                        1.2382045600363996
                    ],
                    [
                        1.3595996322304618,
                        1.2881546942012598
                    ],
                    [
                        1.3615875124155796,
                        1.3381151618969251
                    ],
                    [
                        1.363264926843222,
                        1.3880870167838306
                    ],
                    [
                        1.3646665818707486,
                        1.4380673665543535
                    ],
                    [
                        1.3657459246493346,
                        1.48805571538852
                    ],
                    [
                        1.3665224242048437,
                        1.5380496855093286
                    ],
                    [
                        1.3670138641073544,
                        1.5880472703192194
                    ],
                    [
                        1.3672094772798224,
                        1.6380468876726229
                    ],
                    [
                        1.3671438204501707,
                        1.6880468445644115
                    ],
                    [
                        1.366806938473259,
                        1.7380457096568676
                    ],
                    [
                        1.3661845160279023,
                        1.788041835409765
                    ],
                    [
                        1.365303212974715,
                        1.8380340678557003
                    ],
                    [
                        1.3641687056801235,
                        1.888021195130615
                    ],
                    [
                        1.3627502890659395,
                        1.938001072024307
                    ],
                    [
                        1.3611090779189015,
                        1.9879741290247632
                    ],
                    [
                        1.3592234614449283,
                        2.037938560878964
                    ],
                    [
                        1.357081672554076,
                        2.087892667220155
                    ],
                    [
                        1.3547394683336649,
                        2.1378377778856636
                    ],
                    [
                        1.3521394371078892,
                        2.187770130500226
                    ],
                    [
                        1.3493354333772558,
                        2.2376914442156983
                    ],
                    [
                        1.3462947129817946,
                        2.287598898763858
                    ],
                    [
                        1.3430784218448881,
                        2.3374953462458445
                    ],
                    [
                        1.3396458297078737,
                        2.3873773801981697
                    ],
                    [
                        1.3360509852742082,
                        2.4372479836986063
                    ],
                    [
                        1.3323223652581726,
                        2.4871087638045775
                    ],
                    [
                        1.3284043459173906,
                        2.5369550186733765
                    ],
                    [
                        1.3243648615568528,
                        2.5867915772032446
                    ],
                    [
                        1.320183510960065,
                        2.6366164335220215
                    ],
                    [
                        1.3158347895352327,
                        2.6864269607423714
                    ],
                    [
                        1.3113320223360683,
                        2.7362237988704106
                    ]
                ],
                "id": 2,
                "sourceAngle": 1.5707963267948966,
                "sourcePoint": [
                    1.3,
                    0.0
                ]
            }
        ],
        "Description": "SourcesIds represents sources(or root) branches of each rivers(yes you can setup several rivers in one run). Relations is array{...} of next elements {source_branch_id, {left_child_branch_id, right_child_branch_id} it holds structure of river divided into separate branches. Order of left and right id is important.",
        "Relations": [],
        "SourceIds": [
            1,
            2
        ]
    },
    "Version": "2.6.5"
}